alibabacloud_agentrun20250910/__init__.py
alibabacloud_agentrun20250910/client.py
alibabacloud_agentrun20250910/models/__init__.py
alibabacloud_agentrun20250910/models/_activate_template_mcprequest.py
alibabacloud_agentrun20250910/models/_activate_template_mcpresponse.py
alibabacloud_agentrun20250910/models/_agent_runtime.py
alibabacloud_agentrun20250910/models/_agent_runtime_endpoint.py
alibabacloud_agentrun20250910/models/_agent_runtime_endpoint_result.py
alibabacloud_agentrun20250910/models/_agent_runtime_result.py
alibabacloud_agentrun20250910/models/_agent_runtime_version.py
alibabacloud_agentrun20250910/models/_agent_runtime_version_result.py
alibabacloud_agentrun20250910/models/_ai_fallback_config.py
alibabacloud_agentrun20250910/models/_ai_fallback_service_config.py
alibabacloud_agentrun20250910/models/_ai_service_config.py
alibabacloud_agentrun20250910/models/_apig_llmmodel.py
alibabacloud_agentrun20250910/models/_arms_configuration.py
alibabacloud_agentrun20250910/models/_attach_policy_config.py
alibabacloud_agentrun20250910/models/_browser.py
alibabacloud_agentrun20250910/models/_browser_automation_stream.py
alibabacloud_agentrun20250910/models/_browser_configuration.py
alibabacloud_agentrun20250910/models/_browser_live_view_stream.py
alibabacloud_agentrun20250910/models/_browser_oss_location.py
alibabacloud_agentrun20250910/models/_browser_recording_configuration.py
alibabacloud_agentrun20250910/models/_browser_result.py
alibabacloud_agentrun20250910/models/_browser_session_list_out.py
alibabacloud_agentrun20250910/models/_browser_session_out.py
alibabacloud_agentrun20250910/models/_browser_streams.py
alibabacloud_agentrun20250910/models/_browser_view_port.py
alibabacloud_agentrun20250910/models/_capconfig.py
alibabacloud_agentrun20250910/models/_cert_config.py
alibabacloud_agentrun20250910/models/_code_configuration.py
alibabacloud_agentrun20250910/models/_code_info.py
alibabacloud_agentrun20250910/models/_code_interpreter.py
alibabacloud_agentrun20250910-5.3.1.dist-info/LICENSE
alibabacloud_agentrun20250910-5.3.1.dist-info/METADATA
alibabacloud_agentrun20250910-5.3.1.dist-info/WHEEL
alibabacloud_agentrun20250910-5.3.1.dist-info/top_level.txt
alibabacloud_agentrun20250910-5.3.1.dist-info/RECORD
